trading_indicators/__init__.py
trading_indicators/cli.py
trading_indicators/config.py
trading_indicators/indicators.py
trading_indicators/streamer.py
bitquery_trading_indicators_stream-0.1.1.dist-info/METADATA
bitquery_trading_indicators_stream-0.1.1.dist-info/WHEEL
bitquery_trading_indicators_stream-0.1.1.dist-info/entry_points.txt
bitquery_trading_indicators_stream-0.1.1.dist-info/top_level.txt
bitquery_trading_indicators_stream-0.1.1.dist-info/RECORD
