Metadata-Version: 2.4
Name: bitquery-trading-indicators-stream
Version: 0.1.1
Summary: Real-time trading indicators (RSI, VWAP) streamed from Bitquery GraphQL
Author: Divyasshree
License: MIT
Project-URL: Homepage, https://github.com/divyasshree/trading-indicators
Requires-Python: >=3.10
Requires-Dist: gql[websockets]>=3.5.0
